{"cameraMode":{"drawMode":0,"name":"Shaded","section":"Shading Mode"},"sceneLighting":true,"audioPlay":false,"sceneViewState":{"m_AlwaysRefresh":false,"showFog":true,"showSkybox":true,"showFlares":true,"showImageEffects":true,"showParticleSystems":true,"showVisualEffectGraphs":true,"m_FxEnabled":true},"in2DMode":false,"pivot":{"x":2.1285336017608644,"y":0.8882148861885071,"z":-0.023102905601263047},"rotation":{"x":-0.0019654883071780206,"y":0.9977946281433106,"z":-0.0572454035282135,"w":-0.03413640707731247},"size":0.637350857257843,"orthographic":false}